lektor_markdown_ruby_blocks.py
lektor_markdown_ruby_blocks-0.2.4.dist-info/METADATA
lektor_markdown_ruby_blocks-0.2.4.dist-info/WHEEL
lektor_markdown_ruby_blocks-0.2.4.dist-info/entry_points.txt
lektor_markdown_ruby_blocks-0.2.4.dist-info/licenses/LICENSE
lektor_markdown_ruby_blocks-0.2.4.dist-info/RECORD
