Metadata-Version: 2.1
Name: lektor-markdown-ruby-blocks
Version: 0.2.4
Summary: Introduces a new syntax to Markdown for generating HTML ruby tags
Project-URL: Homepage, https://github.com/25349023/lektor-markdown-ruby-blocks
Author-email: 25349023 <25349023.qq@gmail.com>
License: MIT License
License-File: LICENSE
Keywords: HTML,Lektor,Markdown,plugin,ruby-tag
Classifier: Environment :: Plugins
Classifier: Environment :: Web Environment
Classifier: Framework :: Lektor
Classifier: License :: OSI Approved :: MIT License
Classifier: Operating System :: OS Independent
Classifier: Programming Language :: Python :: 3
Requires-Python: >=3.6
